moodle_xml_parser/__init__.py
moodle_xml_parser/cloze_logic.py
moodle_xml_parser/models.py
moodle_xml_parser/parser.py
moodle_xml_parser-0.3.1.dist-info/licenses/LICENSE
moodle_xml_parser-0.3.1.dist-info/METADATA
moodle_xml_parser-0.3.1.dist-info/WHEEL
moodle_xml_parser-0.3.1.dist-info/top_level.txt
moodle_xml_parser-0.3.1.dist-info/RECORD
