Metadata-Version: 2.4
Name: moodle_xml_parser
Version: 0.3.1
Summary: A robust Python library for parsing Moodle XML quiz questions format into structured data models.
Author-email: Lorenzo Lo Brutto <lorenzolobrutto@gmail.com>
License: MIT License
Project-URL: Homepage, https://github.com/LorenzoLB97/moodle_xml_parser
Keywords: moodle,xml,parser,quiz,cloze,question,questions,multichoice
Classifier: Development Status :: 3 - Alpha
Classifier: Intended Audience :: Developers
Classifier: License :: OSI Approved :: MIT License
Classifier: Programming Language :: Python :: 3
Classifier: Programming Language :: Python :: 3.8
Classifier: Programming Language :: Python :: 3.9
Classifier: Programming Language :: Python :: 3.10
Classifier: Programming Language :: Python :: 3.11
Classifier: Programming Language :: Python :: 3.12
Classifier: Programming Language :: Python :: 3.13
Requires-Python: >=3.8
License-File: LICENSE
Dynamic: license-file
